lockstep/__init__.py
lockstep/errorresult.py
lockstep/fetch_result.py
lockstep/lockstep_api.py
lockstep/lockstep_response.py
lockstep/clients/__init__.py
lockstep/clients/apikeys_client.py
lockstep/clients/appenrollments_client.py
lockstep/clients/applications_client.py
lockstep/clients/attachmentlinks_client.py
lockstep/clients/attachments_client.py
lockstep/clients/codedefinitions_client.py
lockstep/clients/companies_client.py
lockstep/clients/contacts_client.py
lockstep/clients/creditmemosapplied_client.py
lockstep/clients/currencies_client.py
lockstep/clients/customfielddefinitions_client.py
lockstep/clients/customfieldvalues_client.py
lockstep/clients/definitions_client.py
lockstep/clients/featureflags_client.py
lockstep/clients/financialaccount_client.py
lockstep/clients/financialaccountbalancehistory_client.py
lockstep/clients/financialinstitutionaccounts_client.py
lockstep/clients/financialyearsettings_client.py
lockstep/clients/groupaccounts_client.py
lockstep/clients/invoiceaddresses_client.py
lockstep/clients/invoicelines_client.py
lockstep/clients/invoices_client.py
lockstep/clients/journalentries_client.py
lockstep/clients/journalentrylines_client.py
lockstep/clients/leads_client.py
lockstep/clients/magiclinks_client.py
lockstep/clients/notes_client.py
lockstep/clients/payments_client.py
lockstep/clients/paymentsapplied_client.py
lockstep/clients/profilesaccounting_client.py
lockstep/clients/profilesaccountingcontacts_client.py
lockstep/clients/profilescompanies_client.py
lockstep/clients/provisioning_client.py
lockstep/clients/reports_client.py
lockstep/clients/status_client.py
lockstep/clients/sync_client.py
lockstep/clients/transactions_client.py
lockstep/clients/transcriptions_client.py
lockstep/clients/useraccounts_client.py
lockstep/clients/userroles_client.py
lockstep/clients/webhookrules_client.py
lockstep/clients/webhooks_client.py
lockstep/clients/workflowstatuses_client.py
lockstep/models/__init__.py
lockstep_sdk-2023.40.72.dist-info/LICENSE
lockstep_sdk-2023.40.72.dist-info/METADATA
lockstep_sdk-2023.40.72.dist-info/WHEEL
lockstep_sdk-2023.40.72.dist-info/top_level.txt
lockstep_sdk-2023.40.72.dist-info/RECORD
