Metadata-Version: 2.1
Name: lockstep-sdk
Version: 2023.40.72
Summary: Lockstep Platform SDK for Python
Home-page: https://github.com/Lockstep-Network/lockstep-sdk-python
Author: Lockstep
Author-email: developer@lockstep.io
Project-URL: Bug Tracker, https://github.com/Lockstep-Network/lockstep-sdk-python/issues
Classifier: Programming Language :: Python :: 3
Classifier: License :: OSI Approved :: MIT License
Classifier: Operating System :: OS Independent
Requires-Python: >=3.10
License-File: LICENSE
Requires-Dist: requests
